keble_helpers/__init__.py
keble_helpers/aliyun/__init__.py
keble_helpers/aliyun/base.py
keble_helpers/aliyun/oss.py
keble_helpers/aliyun/schemas.py
keble_helpers/aliyun/sts.py
keble_helpers/assembly/__init__.py
keble_helpers/assembly/transcription.py
keble_helpers/aws/__init__.py
keble_helpers/aws/base.py
keble_helpers/aws/schemas.py
keble_helpers/aws/textract.py
keble_helpers/common.py
keble_helpers/datetime.py
keble_helpers/enum.py
keble_helpers/fastapi.py
keble_helpers/file.py
keble_helpers/multithread.py
keble_helpers/np_utils.py
keble_helpers/progress/__init__.py
keble_helpers/progress/main.py
keble_helpers/progress/schemas.py
keble_helpers/pydantic/__init__.py
keble_helpers/pydantic/cloud_storage.py
keble_helpers/pydantic/config.py
keble_helpers/pydantic/schemas.py
keble_helpers/redis_limit.py
keble_helpers-0.2.3.dist-info/LICENSE
keble_helpers-0.2.3.dist-info/METADATA
keble_helpers-0.2.3.dist-info/WHEEL
keble_helpers-0.2.3.dist-info/RECORD
