Metadata-Version: 2.1
Name: keble-helpers
Version: 0.2.3
Summary: 
Author: zhenhao-ma
Author-email: bob0103779@gmail.com
Requires-Python: >=3.10,<4.0
Classifier: Programming Language :: Python :: 3
Classifier: Programming Language :: Python :: 3.10
Classifier: Programming Language :: Python :: 3.11
Classifier: Programming Language :: Python :: 3.12
Requires-Dist: aliyun-python-sdk-core-v3 (>=2,<3)
Requires-Dist: aliyun-python-sdk-sts (>=3,<4)
Requires-Dist: boto3 (>=1,<2)
Requires-Dist: keble-exceptions (>=0.0.3,<1)
Requires-Dist: langchain (>=0,<1)
Requires-Dist: langchain-community (>=0,<1)
Requires-Dist: oss2 (>=2,<3)
Requires-Dist: pydantic (>=2,<3)
Requires-Dist: redis (>=5,<6)
